{"name":"LGNavigationView","description":"Navigation View","baseArr":["LGLinearLayout","LGViewGroup","LGView","NativeObject"],"base":"LGLinearLayout","variables":[],"functions":[{"static":true,"argsstring":"(LuaContext lc)","returnOrg":"LGNavigationView","name":"create","description":"Creates LGNavigationView Object From Lua.","parameters":[{"name":"lc","type":"LuaContext","typeOrg":"LuaContext"}],"return":"LGNavigationView"},{"static":false,"argsstring":"(LuaTranslator lt)","returnOrg":"void","name":"setNavigationItemSelectListener","description":"Set navigation item select listener","parameters":[{"name":"lt","type":"fun(navigationView: LGNavigationView, item: LuaMenu):bool\n","typeOrg":"LuaTranslator"}],"return":"void"}]}