{"variables":[{"default":"= 0xff000000","static":true,"name":"BLACK","description":"black color","type":"final int","typeOrg":"final int"},{"default":"= 0xff0000ff","static":true,"name":"BLUE","description":"blue color","type":"final int","typeOrg":"final int"},{"default":"= 0xff00ffff","static":true,"name":"CYAN","description":"cyan color","type":"final int","typeOrg":"final int"},{"default":"= 0xff444444","static":true,"name":"DKGRAY","description":"dark gray color","type":"final int","typeOrg":"final int"},{"default":"= 0xff888888","static":true,"name":"GRAY","description":"gray color","type":"final int","typeOrg":"final int"},{"default":"= 0xff00ff00","static":true,"name":"GREEN","description":"green color","type":"final int","typeOrg":"final int"},{"default":"= 0xffcccccc","static":true,"name":"LTGRAY","description":"light gray color","type":"final int","typeOrg":"final int"},{"default":"= 0xffff00ff","static":true,"name":"MAGENTA","description":"magenta color","type":"final int","typeOrg":"final int"},{"default":"= 0xffff0000","static":true,"name":"RED","description":"red color","type":"final int","typeOrg":"final int"},{"default":"= 0x00000000","static":true,"name":"TRANSPARENT","description":"transparent color","type":"final int","typeOrg":"final int"},{"default":"= 0xffffffff","static":true,"name":"WHITE","description":"white color","type":"final int","typeOrg":"final int"},{"default":"= 0xffffff00","static":true,"name":"YELLOW","description":"yellow color","type":"final int","typeOrg":"final int"}],"functions":[{"static":true,"argsstring":"(String colorStr)","returnOrg":"LuaColor","name":"FromString","description":"Returns LuaColor from string value. Example #ffffffff or #ffffff","parameters":[{"name":"colorStr","type":"string","typeOrg":"String"}],"return":"LuaColor"},{"static":true,"argsstring":"(int alpha, int red, int green, int blue)","returnOrg":"LuaColor","name":"CreateFromARGB","description":"Returns LuaColor from argb.","parameters":[{"name":"alpha","type":"number","typeOrg":"int"},{"name":"red","type":"number","typeOrg":"int"},{"name":"green","type":"number","typeOrg":"int"},{"name":"blue","type":"number","typeOrg":"int"}],"return":"LuaColor"},{"static":true,"argsstring":"(int red, int green, int blue)","returnOrg":"LuaColor","name":"CreateFromRGB","description":"Returns LuaColor from rgb.","parameters":[{"name":"red","type":"number","typeOrg":"int"},{"name":"green","type":"number","typeOrg":"int"},{"name":"blue","type":"number","typeOrg":"int"}],"return":"LuaColor"},{"static":false,"argsstring":"()","returnOrg":"int","name":"GetColorValue","description":"Returns the integer color value","parameters":[],"return":"number"}],"name":"LuaColor","description":"","baseArr":["LuaColor","NativeObject"],"base":""}